flexi_tag/__init__.py
flexi_tag/apps.py
flexi_tag/codes.py
flexi_tag/exceptions.py
flexi_tag/management/__init__.py
flexi_tag/management/commands/__init__.py
flexi_tag/management/commands/generate_tag_models.py
flexi_tag/utils/__init__.py
flexi_tag/utils/compat.py
flexi_tag/utils/models.py
flexi_tag/utils/service.py
flexi_tag/utils/views.py
dj_flexi_tag-2.1.2.dist-info/LICENSE.txt
dj_flexi_tag-2.1.2.dist-info/METADATA
dj_flexi_tag-2.1.2.dist-info/WHEEL
dj_flexi_tag-2.1.2.dist-info/top_level.txt
dj_flexi_tag-2.1.2.dist-info/RECORD
