Metadata-Version: 2.1
Name: dj-flexi-tag
Version: 2.1.2
Summary: Add tags to any model in Django via ModelViewSet
Home-page: https://bitbucket.org/akinonteam/dj-flexi-tag
Author: Akinon
Author-email: dev@akinon.com
Maintainer: Akinon
Maintainer-email: dev@akinon.com
License: MIT
Project-URL: Documentation, https://dj-flexi-tag.readthedocs.io
Project-URL: Source Code, https://bitbucket.org/akinonteam/dj-flexi-tag
Platform: any
Classifier: Development Status :: 2 - Pre-Alpha
Classifier: Environment :: Web Environment
Classifier: Intended Audience :: Developers
Classifier: Operating System :: OS Independent
Classifier: Programming Language :: Python
Classifier: Programming Language :: Python :: 3.5
Classifier: Programming Language :: Python :: 3.6
Classifier: Programming Language :: Python :: 3.7
Classifier: Programming Language :: Python :: 3.8
Classifier: Programming Language :: Python :: 3.9
Classifier: Programming Language :: Python :: 3.10
Classifier: Programming Language :: Python :: 3.11
Classifier: Programming Language :: Python :: 3.12
Classifier: Framework :: Django
Classifier: Framework :: Django :: 1.11
Classifier: Framework :: Django :: 2.0
Classifier: Framework :: Django :: 2.1
Classifier: Framework :: Django :: 2.2
Classifier: Framework :: Django :: 3.0
Classifier: Framework :: Django :: 3.1
Classifier: Framework :: Django :: 3.2
Classifier: Framework :: Django :: 4.0
Classifier: Framework :: Django :: 4.1
Classifier: Framework :: Django :: 4.2
Classifier: Framework :: Django :: 5.0
Requires-Python: >=3.5
License-File: LICENSE.txt
Requires-Dist: Django <5.1,>=1.11
Requires-Dist: djangorestframework <=4.0,>=3.4.3
Requires-Dist: psycopg2-binary
Requires-Dist: pytz
Requires-Dist: typing-extensions
Provides-Extra: dev
Requires-Dist: black ==21.5b1 ; extra == 'dev'
Requires-Dist: isort ==5.0.4 ; extra == 'dev'
Requires-Dist: tox ; extra == 'dev'
Requires-Dist: click ==7.1.2 ; extra == 'dev'
Provides-Extra: docs
Requires-Dist: sphinx-rtd-theme ==1.2.0 ; extra == 'docs'
Requires-Dist: sphinx ==5.3.0 ; extra == 'docs'
Requires-Dist: docutils >=0.18 ; extra == 'docs'
Provides-Extra: test
Requires-Dist: mock ; extra == 'test'
Requires-Dist: importlib-metadata <5.0,>=1.4.0 ; (python_version == "3.7") and extra == 'test'
